{
  "users": [
    {
      "user": {
        "fullName": "tomas",
        "email": "mekabaj544@ippals.com",
        "password": "password123",
        "rol": "superAdmin",
        "charge": "superAdmin",
        "isPending": false,
        "photoURL": "https://images-ext-1.discordapp.net/external/bOgWlEZbAuRA9YHgfBeV4kYBRR9UL9c5syYQC2kfi8g/https/i.ibb.co/m51pLc4/Nueva-imagen-de-mapa-de-bits.png"
      }
    },
    {
      "user": {
        "fullName": "abacob",
        "email": "abacop@gmail.com",
        "password": "password123",
        "rol": "adminProviders",
        "charge": "admin parque",
        "isPending": false,
        "photoURL": "https://images-ext-1.discordapp.net/external/FU9IcH7tprwfHECW67zF6a16fygSAFB8CtZg0WmzSg4/https/i.ibb.co/bPMbbst/Nueva-imagen-de-mapa-de-bits.png"
      }
    },
    {
      "user": {
        "fullName": "marcelo",
        "email": "marcelo@gmail.com",
        "password": "password123",
        "rol": "adminReviews",
        "charge": "superAdmin",
        "isPending": false,
        "photoURL": "https://images-ext-1.discordapp.net/external/02yh0JpCQ72O-ZvFjXRPg7zKQJaOY_A7uIMROqEzt4Q/https/i.ibb.co/ThJG0z5/Nueva-imagen-de-mapa-de-bits.png"
      }
    },
    {
      "user": {
        "fullName": "fabio",
        "email": "fabio@gmail.com",
        "password": "password123",
        "rol": "adminReviews",
        "charge": "superAdmin",
        "isPending": false,
        "photoURL": "https://images-ext-2.discordapp.net/external/lSMB_JkV57AsbO85XUkY9o54sQIosvj2S_qXF-ZEBLg/https/i.ibb.co/pRVjmBj/Nueva-imagen-de-mapa-de-bits.png"
      }
    },
    {
      "user": {
        "fullName": "marcos",
        "email": "marcos@gmail.com",
        "password": "password123",
        "rol": "checker",
        "charge": "developer",
        "isPending": false,
        "photoURL": "https://images-ext-1.discordapp.net/external/8WJLkrXqzVS6iocp-CYsV1Kx1svhIbNcMVgh0iyAazM/https/i.ibb.co/jD0nTcK/Nueva-imagen-de-mapa-de-bits.png"
      },
      "company": {
        "name": "Metalurgica Guemes"
      }
    },
    {
      "user": {
        "fullName": "nico",
        "email": "nico@gmail.com",
        "adress": "address3",
        "password": "password123",
        "rol": "checker",
        "charge": "limpieza",
        "isPending": false,
        "photoURL": "https://media.licdn.com/dms/image/D5603AQHkepKPTkGTWw/profile-displayphoto-shrink_800_800/0/1674070138632?e=1686182400&v=beta&t=fO-b69A_cs3bmuJJl3DGd9famR9lVS0Y5KS_HMgKSrw"
      },
      "company": {
        "name": "Agrotv"
      }
    },
    {
      "user": {
        "fullName": "matias",
        "email": "matias@gmail.com",
        "adress": "address4",
        "password": "password123",
        "charge": "tecnico",
        "rol": "checker",
        "isPending": false,
        "photoURL": "https://images-ext-1.discordapp.net/external/1DdJrcwYHp6lJjKWYi4Bt_JspIxBjVDDfOIPvVt3iq8/https/i.ibb.co/sFB4dw2/Nueva-imagen-de-mapa-de-bits.png"
      },
      "company": {
        "name": "Paqueta"
      }
    },
    {
      "user": {
        "fullName": "julian",
        "email": "julian@gmail.com",
        "adress": "address5",
        "password": "password123",
        "rol": "adminReviews",
        "charge": "checker",
        "isPending": false,
        "photoURL": "https://images-ext-1.discordapp.net/external/lpTQLzHk7RxP1z_2h_Lvog_CKAoQS6Z3VZfjiJAmlJQ/https/i.ibb.co/PwrSN9L/Nueva-imagen-de-mapa-de-bits.png"
      },
      "company": {
        "name": "Testmic"
      }
    },
    {
      "user": {
        "fullName": "pedro",
        "email": "pedro@gmail.com",
        "password": "password123",
        "charge": "consejero",
        "isPending": false,
        "photoURL": "https://media.licdn.com/dms/image/D4D03AQFgomyTUrXE0w/profile-displayphoto-shrink_800_800/0/1667419747202?e=1686182400&v=beta&t=5-acGKwirT_ojNd2JiF2lX3IhExslESIdd_syzc3S6k"
      },
      "company": {
        "name": "Metalurgica Guemes"
      }
    },
    {
      "user": {
        "fullName": "leandro",
        "email": "leandro@gmail.com",
        "password": "password123",
        "charge": "mantenimiento",
        "isPending": false,
        "photoURL": "https://media.licdn.com/dms/image/C5603AQGZ_xVLu8R8Uw/profile-displayphoto-shrink_800_800/0/1618844106240?e=1686182400&v=beta&t=XslIMKU8b8_eVfY4rDu-ricbZ_iDh_lljOUO130XVBo"
      },
      "company": {
        "name": "Agrotv"
      }
    },
    {
      "user": {
        "fullName": "martin",
        "email": "martin@gmail.com",
        "password": "password123",
        "charge": "administrativo",
        "isPending": false,
        "photoURL": "https://media.licdn.com/dms/image/D4D35AQFsMUc_3dgUNQ/profile-framedphoto-shrink_800_800/0/1651522726300?e=1681329600&v=beta&t=Oi9wMFPIov8x3rf2MpDtIcxCnT60Y600gWaO4NvHOqA"
      },
      "company": {
        "name": "Testmic"
      }
    },
    {
      "user": {
        "fullName": "franciso",
        "email": "francisco@gmail.com",
        "password": "password123",
        "charge": "limpieza",
        "isPending": false,
        "photoURL": "https://media.licdn.com/dms/image/D4D03AQFAbpvXm7AfYg/profile-displayphoto-shrink_800_800/0/1673275784982?e=1686182400&v=beta&t=KCZ1v--dG0Vp_3g5uPMSXHNK2GgSgJ3-gW4na8yRutU"
      },
      "company": {
        "name": "Testmic"
      }
    },
    {
      "user": {
        "fullName": "julieta",
        "email": "julieta@gmail.com",
        "password": "password123",
        "charge": "developer",
        "isPending": true,
        "photoURL": "https://media.licdn.com/dms/image/D4E03AQFImA7hzZn8eA/profile-displayphoto-shrink_800_800/0/1674687013206?e=1686182400&v=beta&t=knI1mpy-w1SdlQoqJDU74C2LYd1rjpet5lAnME5y3Jk"
      },
      "company": {
        "name": "Paqueta"
      }
    }
  ]
}
